{"assets":{"BB7D6D39023163CD4AEA82C7FBB6CA3A":{"type":"texture","index":1,"url":{"native":"assets\/D04AA57C-F97A-4570-B47C-0B25C004200F.pdf"},"width":1920,"height":1080},"1777618A31AB22642F4B9DEF9B12CFD1":{"type":"texture","index":0,"url":{"native":"assets\/D04AA57C-F97A-4570-B47C-0B25C004200F.pdf"},"width":1920,"height":1080}},"events":[{"effects":[{"beginTime":0,"baseLayer":{"animations":[],"initialState":{"affineTransform":[1,0,0,1,0,0],"masksToBounds":false,"rotation":0,"scale":1,"position":{"pointX":960,"pointY":540},"width":1920,"sublayerTransform":[1,0,0,0,0,1,0,0,0,0,1,0,0,0,0,1],"contentsRect":{"y":0,"x":0,"width":1,"height":1},"opacity":1,"edgeAntialiasingMask":251658240,"height":1080,"hidden":false,"anchorPoint":{"pointX":0.5,"pointY":0.5}},"objectID":"0","layers":[{"animations":[],"initialState":{"affineTransform":[1,0,0,1,0,0],"masksToBounds":false,"rotation":0,"scale":1,"position":{"pointX":960,"pointY":540},"width":1920,"sublayerTransform":[1,0,0,0,0,1,0,0,0,0,1,-0.00035007912466775983,0,0,0,1],"contentsRect":{"y":0,"x":0,"width":1,"height":1},"opacity":1,"edgeAntialiasingMask":251658240,"height":1080,"hidden":false,"anchorPoint":{"pointX":0.5,"pointY":0.5}},"layers":[{"animations":[],"layers":[],"texturedRectangle":{"isBackgroundTexture":false,"singleTextureOpacity":1,"textureType":0,"textBaseline":0,"textXHeight":0,"isVerticalText":false},"initialState":{"affineTransform":[1,0,0,1,0,0],"masksToBounds":false,"rotation":0,"scale":1,"position":{"pointX":960,"pointY":540},"width":1920,"sublayerTransform":[1,0,0,0,0,1,0,0,0,0,1,0,0,0,0,1],"contentsRect":{"y":0,"x":0,"width":1,"height":1},"opacity":1,"edgeAntialiasingMask":0,"height":1080,"hidden":false,"anchorPoint":{"pointX":0.5,"pointY":0.5}},"texture":"BB7D6D39023163CD4AEA82C7FBB6CA3A"},{"animations":[{"additive":false,"timeOffset":0,"beginTime":0,"from":{"scalar":false},"repeatCount":0,"fillMode":"both","duration":0.001,"autoreverses":false,"property":"hidden","to":{"scalar":true},"removedOnCompletion":false}],"layers":[],"texturedRectangle":{"isBackgroundTexture":false,"singleTextureOpacity":1,"textureType":0,"textBaseline":0,"textXHeight":0,"isVerticalText":false},"initialState":{"affineTransform":[1,0,0,1,0,0],"masksToBounds":false,"rotation":0,"scale":1,"position":{"pointX":960,"pointY":540},"width":1920,"sublayerTransform":[1,0,0,0,0,1,0,0,0,0,1,0,0,0,0,1],"contentsRect":{"y":0,"x":0,"width":1,"height":1},"opacity":1,"edgeAntialiasingMask":0,"height":1080,"hidden":false,"anchorPoint":{"pointX":0.5,"pointY":0.5}},"texture":"1777618A31AB22642F4B9DEF9B12CFD1"}]}]},"effects":[],"duration":0.001,"type":"transition","attributes":{"direction":0},"name":"none","objectID":"0"}],"automaticPlay":false,"hyperlinks":[],"accessibility":[{"text":"equation.pdf","targetRectangle":{"y":350.91887187066482,"x":841.60658500000159,"width":88.257332120647106,"height":50.660876265196066}},{"text":"equation.pdf","targetRectangle":{"y":255,"x":321.84799856948848,"width":21.742990654205585,"height":50.660876265196066}},{"text":"equation.pdf","targetRectangle":{"y":469.23526763916016,"x":1403.1423950195312,"width":36.275820400922385,"height":31.786000000000001}},{"text":"Schrödinger’s bridge problem","targetRectangle":{"y":52,"x":193.3040000000002,"width":1533.3919999999998,"height":132.751220703125}},{"text":"equation.pdf","targetRectangle":{"y":711.23788826338443,"x":682.82959741536001,"width":647.17405712240475,"height":53.311020787250868}},{"text":"equation.pdf","targetRectangle":{"y":350.91887187066482,"x":706.04000673801602,"width":84.878578261985467,"height":52.878770133045236}},{"text":"equation.pdf","targetRectangle":{"y":466.24106979370117,"x":573.69573974609375,"width":38.953940400922534,"height":32.243240000000014}},{"text":"equation.pdf","targetRectangle":{"y":350.91887187066482,"x":1010.5759171206487,"width":88.257332120647106,"height":50.660876265196066}},{"text":"equation.pdf","targetRectangle":{"y":350.91887187066482,"x":541.2319985694885,"width":84.096008168527533,"height":53.311020787250868}},{"text":"Cloud of ￼ independent Brownian particles ","targetRectangle":{"y":255,"x":174.49999856948853,"width":698.50699065420565,"height":50.660876265196066}},{"text":"Empirical distributions ￼ and ￼ at ￼ and ￼","targetRectangle":{"y":306.66887187066482,"x":174.49999856948853,"width":924.33325067180726,"height":97.561020787250811}},{"text":"Particles have been transported in an unlikely way ","targetRectangle":{"y":492.48788826338438,"x":174.49999856948853,"width":814.10399999999981,"height":86.242004394531193}},{"text":"Of the many possible (unlikely) ways, which one is the most likely? [Lénoard 2014]","targetRectangle":{"y":579.73788826338432,"x":174.49999856948853,"width":1250.4480000000003,"height":86.24200439453125}},{"text":"￼","targetRectangle":{"y":666.98788826338432,"x":682.82959741536001,"width":647.17405712240497,"height":97.561020787250982}},{"text":"A dynamics formulation of entropic-regularized optimal transport [Vallani 2009]","targetRectangle":{"y":765.55690465610405,"x":174.49999856948853,"width":1202.3159999999998,"height":86.24200439453125}},{"text":"￼","targetRectangle":{"y":852.80690465610405,"x":506.06302430718654,"width":1000.707203338752,"height":151.85605525528661}},{"text":"equation.pdf","targetRectangle":{"y":897.05690465610394,"x":506.06302430718654,"width":1000.707203338752,"height":107.60605525528661}}],"baseLayer":{"animations":[],"initialState":{"affineTransform":[1,0,0,1,0,0],"masksToBounds":false,"rotation":0,"scale":1,"position":{"pointX":960,"pointY":540},"width":1920,"sublayerTransform":[1,0,0,0,0,1,0,0,0,0,1,0,0,0,0,1],"contentsRect":{"y":0,"x":0,"width":1,"height":1},"opacity":1,"edgeAntialiasingMask":251658240,"height":1080,"hidden":false,"anchorPoint":{"pointX":0.5,"pointY":0.5}},"objectID":"0","layers":[{"animations":[],"initialState":{"affineTransform":[1,0,0,1,0,0],"masksToBounds":false,"rotation":0,"scale":1,"position":{"pointX":960,"pointY":540},"width":1920,"sublayerTransform":[1,0,0,0,0,1,0,0,0,0,1,-0.00035007912466775983,0,0,0,1],"contentsRect":{"y":0,"x":0,"width":1,"height":1},"opacity":1,"edgeAntialiasingMask":251658240,"height":1080,"hidden":false,"anchorPoint":{"pointX":0.5,"pointY":0.5}},"layers":[{"animations":[],"layers":[],"texturedRectangle":{"isBackgroundTexture":false,"singleTextureOpacity":1,"textureType":0,"textBaseline":0,"textXHeight":0,"isVerticalText":false},"initialState":{"affineTransform":[1,0,0,1,0,0],"masksToBounds":false,"rotation":0,"scale":1,"position":{"pointX":960,"pointY":540},"width":1920,"sublayerTransform":[1,0,0,0,0,1,0,0,0,0,1,0,0,0,0,1],"contentsRect":{"y":0,"x":0,"width":1,"height":1},"opacity":1,"edgeAntialiasingMask":0,"height":1080,"hidden":false,"anchorPoint":{"pointX":0.5,"pointY":0.5}},"texture":"1777618A31AB22642F4B9DEF9B12CFD1"}]}]}}]}